optimizean/__init__.py
optimizean/config.py
optimizean/contents.py
optimizean/dependency.py
optimizean/display.py
optimizean/localization.py
optimizean/main.py
optimizean/userid.py
optimizean/utils.py
optimizean-1.1.2.dist-info/LICENSE
optimizean-1.1.2.dist-info/METADATA
optimizean-1.1.2.dist-info/WHEEL
optimizean-1.1.2.dist-info/entry_points.txt
optimizean-1.1.2.dist-info/RECORD
