Metadata-Version: 2.1
Name: optimizean
Version: 1.1.2
Summary: Have any questions? Take a moment to find out!
Home-page: https://github.com/optimizean/READO
License: MIT
Keywords: hello world,python,profile,readme
Author: optimizean
Author-email: optimize.an@gmail.com
Maintainer: optimizean
Maintainer-email: optimize.an@gmail.com
Requires-Python: >=3.8,<4.0
Classifier: License :: OSI Approved :: MIT License
Classifier: Programming Language :: Python :: 3
Classifier: Programming Language :: Python :: 3.8
Classifier: Programming Language :: Python :: 3.9
Classifier: Programming Language :: Python :: 3.10
Classifier: Programming Language :: Python :: 3.11
Classifier: Programming Language :: Python :: 3.12
Requires-Dist: requests (>=2.32.3,<3.0.0)
Requires-Dist: rich (>=13.7.1,<14.0.0)
Project-URL: Bug Tracker, https://github.com/optimizean/READO/issues
Project-URL: Repository, https://github.com/optimizean/READO
